reviewington/__init__.py
reviewington/about.txt
reviewington/about_reader.py
reviewington/app.py
reviewington/comment.py
reviewington/configurator.py
reviewington/diff2html.py
reviewington/discussion.py
reviewington/repo_file.py
reviewington/repository.py
reviewington/search.py
reviewington/tags.py
reviewington/github_action_template/review_checker.yml
reviewington/static/css/index.css
reviewington/static/css/main.css
reviewington/static/img/Reviewington.png
reviewington/static/img/loading.gif
reviewington/templates/files.html
reviewington/templates/home.html
reviewington/templates/loading.html
reviewington/templates/reviews.html
reviewington-1.0.0.data/scripts/rton
test/__init__.py
test/test_comment.py
test/test_repository.py
reviewington-1.0.0.dist-info/LICENSE
reviewington-1.0.0.dist-info/METADATA
reviewington-1.0.0.dist-info/WHEEL
reviewington-1.0.0.dist-info/top_level.txt
reviewington-1.0.0.dist-info/RECORD
